gittoc/__init__.py
gittoc/gittoc.py
test/__init__.py
test/basic.py
git_toc-1.0.2.dist-info/LICENSE
git_toc-1.0.2.dist-info/METADATA
git_toc-1.0.2.dist-info/WHEEL
git_toc-1.0.2.dist-info/entry_points.txt
git_toc-1.0.2.dist-info/top_level.txt
git_toc-1.0.2.dist-info/RECORD
