Metadata-Version: 2.1
Name: git-toc
Version: 1.0.2
Summary: Tool to generates TOC for GitHub markdown
Home-page: https://github.com/PrzemekWirkus/git-toc
Author: Przemyslaw Wirkus
Author-email: Przemyslaw.Wirkus@arm.com
Maintainer: Przemyslaw Wirkus
Maintainer-email: Przemyslaw.Wirkus@arm.com
License: Apache-2.0
License-File: LICENSE
